CHANGES.rst
MANIFEST.in
README.rst
setup.cfg
setup.py
src/ps/__init__.py
src/ps.plone.basepolicy.egg-info/PKG-INFO
src/ps.plone.basepolicy.egg-info/SOURCES.txt
src/ps.plone.basepolicy.egg-info/dependency_links.txt
src/ps.plone.basepolicy.egg-info/entry_points.txt
src/ps.plone.basepolicy.egg-info/namespace_packages.txt
src/ps.plone.basepolicy.egg-info/not-zip-safe
src/ps.plone.basepolicy.egg-info/requires.txt
src/ps.plone.basepolicy.egg-info/top_level.txt
src/ps/plone/__init__.py
src/ps/plone/basepolicy/__init__.py
src/ps/plone/basepolicy/configure.zcml
src/ps/plone/basepolicy/profiles.zcml
src/ps/plone/basepolicy/testing.py
src/ps/plone/basepolicy/profiles/default/mailhost.xml
src/ps/plone/basepolicy/profiles/default/metadata.xml
src/ps/plone/basepolicy/profiles/default/properties.xml
src/ps/plone/basepolicy/profiles/default/propertiestool.xml
src/ps/plone/basepolicy/profiles/default/rolemap.xml
src/ps/plone/basepolicy/profiles/default/tinymce.xml
src/ps/plone/basepolicy/tests/__init__.py
src/ps/plone/basepolicy/tests/test_settings.py
src/ps/plone/basepolicy/tests/test_setup.py